britant/__init__.py
britant-0.0.0.dist-info/METADATA
britant-0.0.0.dist-info/WHEEL
britant-0.0.0.dist-info/top_level.txt
britant-0.0.0.dist-info/RECORD
