Metadata-Version: 2.1
Name: britant
Version: 0.0.0
Summary: Coming soon
Author-email: britant <test@test.com>
